AUTHORS.rst
CONTRIBUTING.rst
LICENSE
MANIFEST.in
README.md
requirements-test.txt
setup.cfg
setup.py
bin/zeef
pyzeef/__init__.py
pyzeef/markdown_template.md
pyzeef.egg-info/PKG-INFO
pyzeef.egg-info/SOURCES.txt
pyzeef.egg-info/dependency_links.txt
pyzeef.egg-info/not-zip-safe
pyzeef.egg-info/requires.txt
pyzeef.egg-info/top_level.txt
tests/__init__.py
tests/test_pyzeef.py