Metadata-Version: 1.1
Name: pyzeef
Version: 0.1.2
Summary: Python ZEEF API handler
Home-page: https://github.com/ellisonleao/pyzeef
Author: Ellison Leão
Author-email: ellisonleao@gmail.com
License: MIT
Keywords: pyzeef
Platform: UNKNOWN
Classifier: Development Status :: 2 - Pre-Alpha
Classifier: Intended Audience :: Developers
Classifier: License :: OSI Approved :: BSD License
Classifier: Natural Language :: English
Classifier: Programming Language :: Python :: 2
Classifier: Programming Language :: Python :: 2.6
Classifier: Programming Language :: Python :: 2.7
